ethnicseer/__init__.py
ethnicseer/ethnic_classifier.py
ethnicseer/ethnicseer_meta.pk
ethnicseer/ethnicseer_model.pk
ethnicseer/ethnicseer_vec.pk
ethnicseer/experiment.py
ethnicseer/__pycache__/__init__.cpython-39.pyc
ethnicseer/__pycache__/ethnic_classifier.cpython-39.pyc
ethnicseer/__pycache__/experiment.cpython-39.pyc
ethnicseer-0.1.2.dist-info/LICENSE
ethnicseer-0.1.2.dist-info/METADATA
ethnicseer-0.1.2.dist-info/WHEEL
ethnicseer-0.1.2.dist-info/top_level.txt
ethnicseer-0.1.2.dist-info/RECORD
