Metadata-Version: 2.1
Name: ethnicseer
Version: 0.1.2
Summary: name-ethnicity classifier
Home-page: https://github.com/pucktada/ethnicseer
Author: Pucktada Treeratpituk
Author-email: pucktadt@bot.or.th
License: Apache Software License 2.0
Platform: UNKNOWN
Requires-Python: >=3.7.6
License-File: LICENSE
Requires-Dist: abydos
Requires-Dist: scikit-learn
Requires-Dist: nltk
